alfeneve/__init__.py
alfeneve/alfen.py
alfeneve/cli.py
alfeneve/config.py
alfeneve-0.6.1.dist-info/AUTHORS
alfeneve-0.6.1.dist-info/LICENSE
alfeneve-0.6.1.dist-info/METADATA
alfeneve-0.6.1.dist-info/WHEEL
alfeneve-0.6.1.dist-info/entry_points.txt
alfeneve-0.6.1.dist-info/pbr.json
alfeneve-0.6.1.dist-info/top_level.txt
alfeneve-0.6.1.dist-info/RECORD
