Metadata-Version: 2.1
Name: alfeneve
Version: 0.6.1
Summary: API Client for Alfen Eve EV charging units.
Home-page: https://gitlab.com/LordGaav/alfen-eve
Author: Nick Douma
Author-email: n.douma@nekoconeko.nl
License: MIT
Keywords: alfeneve
Platform: UNKNOWN
Classifier: Development Status :: 4 - Beta
Classifier: Intended Audience :: Developers
Classifier: License :: OSI Approved :: MIT License
Classifier: Operating System :: Unix
Classifier: Programming Language :: Python :: 3
Classifier: Programming Language :: Python :: 3.7
Classifier: Programming Language :: Python :: 3.8
Classifier: Topic :: Utilities
License-File: LICENSE
License-File: AUTHORS
Requires-Dist: pbr (>=1.9)
Requires-Dist: setuptools (>=17.1)
Requires-Dist: requests
Requires-Dist: tabulate
Requires-Dist: iso8601
Requires-Dist: tzlocal
Provides-Extra: cli
Requires-Dist: omniconf[yaml] ; extra == 'cli'
